rest_whatever/__init__.py
rest_whatever/app.py
rest_whatever/auth.py
rest_whatever/cli.py
rest_whatever/config.py
rest_whatever/database.py
rest_whatever/middleware.py
rest_whatever/models.py
rest_whatever/routers/__init__.py
rest_whatever/routers/databases.py
rest_whatever/routers/records.py
rest_whatever/routers/tables.py
rest_whatever/routers/uploads.py
rest_whatever/utils.py
rest_whatever-0.6.0.dist-info/WHEEL
rest_whatever-0.6.0.dist-info/entry_points.txt
rest_whatever-0.6.0.dist-info/METADATA
rest_whatever-0.6.0.dist-info/RECORD
