Metadata-Version: 2.3
Name: rest-whatever
Version: 0.6.0
Summary: 通用数据库REST API服务
Requires-Dist: fastapi>=0.116.0
Requires-Dist: pydantic>=2.11.7
Requires-Dist: sqlalchemy[asyncio]>=2.0.41
Requires-Dist: uvicorn[standard]>=0.22.0
Requires-Dist: aiomysql>=0.2.0
Requires-Dist: aiosqlite>=0.19.0
Requires-Dist: asyncpg>=0.29.0
Requires-Dist: polars>=0.20.0
Requires-Dist: pyarrow>=12.0.0
Requires-Dist: python-multipart>=0.0.6
Requires-Dist: fire>=0.5.0
Requires-Dist: httpx>=0.25.0
Requires-Python: >=3.12
